{"Id":"82","UserId":"8","GroupId":"3","FolderId":"4","Date":"16. 10. 2014 13:49:49","Title":"Jozef II. Habsburg","KeyWords":["Jozef II. Habsburg","1741 - 1790","jozef\u00ednske reformy"],"References":["MATULA, V. et al.: Dejiny Slovenska II. 1526 - 1848. 1. vyd. Bratislava : Veda, 1987. 856 s."],"Content":"<p>\u00a0 \u00a0<a class=\"fancybox\" href=\"groups\/3\/articles\/4\/82n\/Jozef II..jpg\">Jozef II. Habsburg <\/a>bol cis\u00e1rom Sv\u00e4tej r\u00ed\u0161e r\u00edmskej nemeck\u00e9ho n\u00e1roda v obdob\u00ed 1765 - 1790, spoluvl\u00e1dcom Rak\u00faskej monarchie s jeho matkou, M\u00e1riou Ter\u00e9ziou, v obdob\u00ed 1765 - 1780 a vl\u00e1dcom Rak\u00faskej monarchie v obdob\u00ed 1780 - 1790.\u00a0<\/p>\r\n<p>\u00a0 \u00a0Jozef II. \u017eil v obdob\u00ed 13. 3. 1741 - 20. 2. 1790. Bol synom M\u00e1rie Ter\u00e9zie a Franti\u0161ka I. Lotrinsk\u00e9ho. Spolu so svojou matkou, M\u00e1riou Ter\u00e9ziou a svoj\u00edm mlad\u0161\u00edm bratom, Leopoldom II., predstavoval obdobie tzv. osvieteneck\u00e9ho absolutizmu v Rak\u00faskej monarchii. Jozef dokon\u010doval reformy svojej matky, no pri\u010dinil sa o viacero vlastn\u00fdch reforiem a to hlavne:<\/p>\r\n<ol>\r\n<li><strong>Toleran\u010dn\u00fd patent<\/strong>\u00a0z roku 1781 - zrovnopr\u00e1v\u0148oval postavenie kres\u0165ansk\u00fdch cirkv\u00ed v monarchii.<\/li>\r\n<li><strong>Podpora z\u00e1kladn\u00fdch \u0161k\u00f4l\u00a0<\/strong>- za keho vl\u00e1dy zniklo viac ne\u017e 500 z\u00e1kladn\u00fdch \u0161k\u00f4l<\/li>\r\n<li><strong>Zru\u0161enie nevo\u013en\u00edctva\u00a0<\/strong>- 2. 10. 1785\u00a0<\/li>\r\n<li><strong>Zavedenie nem\u010diny ako \u00faradn\u00e9ho jazyka<\/strong><\/li>\r\n<li><strong>Da\u0148ov\u00e1 reforma\u00a0<\/strong><\/li>\r\n<li><strong>S\u00fapis obyvate\u013estva a o\u010d\u00eds\u013eovanie v\u0161etk\u00fdch domov<\/strong><\/li>\r\n<\/ol>\r\n<p><strong>\u00a0 \u00a0<\/strong>Mesiac pred svoj\u00edm \u00famrt\u00edm v\u0161ak v\u00e4\u010d\u0161inu zo svojich reforiem odvolal kv\u00f4li n\u00e1tlaku zo strany \u0161\u013eachty. V platnosti ponechal len toleran\u010dn\u00fd patent, zru\u0161enie nevo\u013en\u00edctva a zalo\u017een\u00e9 farnosti.<\/p>\r\n<p>\u00a0 \u00a0N\u00e1stupcom Jozefa II. sa v roku 1790 stal jeho brat, Leopold II.<\/p>\r\n<p>\u00a0<\/p>"}